skeleton_says/__init__.py
skeleton_says/__main__.py
skeleton_says/_version_git.py
skeleton_says/say.py
skeleton_says/skeleton.jinja2
skeleton_says-1.0.dist-info/LICENSE
skeleton_says-1.0.dist-info/METADATA
skeleton_says-1.0.dist-info/WHEEL
skeleton_says-1.0.dist-info/entry_points.txt
skeleton_says-1.0.dist-info/top_level.txt
skeleton_says-1.0.dist-info/RECORD
