Metadata-Version: 2.1
Name: skeleton-says
Version: 1.0
Summary: Commandline application with a talking skeleton
Home-page: https://github.com/thomascobb/skeleton-says
Author: Skeleton
Author-email: skeleton@example.com
License: Apache License 2.0
Platform: UNKNOWN
Classifier: Development Status :: 4 - Beta
Classifier: License :: OSI Approved :: Apache Software License
Classifier: Programming Language :: Python :: 3.7
Classifier: Programming Language :: Python :: 3.8
Classifier: Programming Language :: Python :: 3.9
Requires-Python: >=3.6
License-File: LICENSE
Requires-Dist: jinja2
Provides-Extra: dev
Requires-Dist: black (==21.9b0) ; extra == 'dev'
Requires-Dist: isort (>5.0) ; extra == 'dev'
Requires-Dist: flake8-isort ; extra == 'dev'
Requires-Dist: mypy ; extra == 'dev'
Requires-Dist: pytest ; extra == 'dev'
Requires-Dist: pytest-cov ; extra == 'dev'
Requires-Dist: sphinx-rtd-theme-github-versions ; extra == 'dev'
Requires-Dist: pre-commit ; extra == 'dev'
